weatherCN/__init__.py
weatherCN/app.py
weatherCN/data/city.json
weatherChina/__init__.py
weatherChina/app.py
weatherChina/data/city.json
weatherChina-0.0.0.6.dist-info/LICENSE
weatherChina-0.0.0.6.dist-info/METADATA
weatherChina-0.0.0.6.dist-info/WHEEL
weatherChina-0.0.0.6.dist-info/entry_points.txt
weatherChina-0.0.0.6.dist-info/top_level.txt
weatherChina-0.0.0.6.dist-info/RECORD
