Metadata-Version: 2.1
Name: weatherChina
Version: 0.0.0.6
Summary: The most simple way to get China city weather through python.
Home-page: http://github.com/Peiiii/weatherChina
Author: Wang Pei
Author-email: 1535376447@qq.com
License: UNKNOWN
Platform: UNKNOWN
Classifier: Programming Language :: Python :: 3
Classifier: License :: OSI Approved :: MIT License
Classifier: Operating System :: OS Independent
Requires-Python: >=3.0
Requires-Dist: requests
